calmjs.dev-2.3.0-py3.6-nspkg.pth
calmjs/dev/README.rst
calmjs/dev/__init__.py
calmjs/dev/artifact.py
calmjs/dev/cli.py
calmjs/dev/dist.py
calmjs/dev/karma.py
calmjs/dev/main.js
calmjs/dev/runtime.py
calmjs/dev/toolchain.py
calmjs/dev/utils.py
calmjs/dev/tests/__init__.py
calmjs/dev/tests/test_artifact.py
calmjs/dev/tests/test_cli.py
calmjs/dev/tests/test_dist.py
calmjs/dev/tests/test_fail.js
calmjs/dev/tests/test_karma.py
calmjs/dev/tests/test_main.js
calmjs/dev/tests/test_runtime.py
calmjs/dev/tests/test_toolchain.py
calmjs/dev/tests/test_utils.py
calmjs.dev-2.3.0.dist-info/METADATA
calmjs.dev-2.3.0.dist-info/RECORD
calmjs.dev-2.3.0.dist-info/WHEEL
calmjs.dev-2.3.0.dist-info/entry_points.txt
calmjs.dev-2.3.0.dist-info/namespace_packages.txt
calmjs.dev-2.3.0.dist-info/package.json
calmjs.dev-2.3.0.dist-info/top_level.txt
